lcboapi/__init__.py
lcboapi-0.2.1.dist-info/METADATA
lcboapi-0.2.1.dist-info/RECORD
lcboapi-0.2.1.dist-info/WHEEL
lcboapi-0.2.1.dist-info/top_level.txt
tests/__init__.py
tests/constants.py
tests/test_datasets.py
tests/test_inventories.py
tests/test_products.py
tests/test_stores.py
