Metadata-Version: 2.1
Name: lcboapi
Version: 0.2.1
Summary: Python wrapper for the unofficial LCBO API
Home-page: https://github.com/shamrt/LCBOAPI
Author: Shane Martin
Author-email: dev.sh@nemart.in
License: MIT License
Download-URL: https://github.com/shamrt/LCBOAPI/archive/v0.2.1.tar.gz
Keywords: api,lcbo
Platform: UNKNOWN
Classifier: Development Status :: 4 - Beta
Classifier: Intended Audience :: Developers
Classifier: License :: OSI Approved :: BSD License
Classifier: Natural Language :: English
Classifier: Operating System :: OS Independent
Classifier: Programming Language :: Python
Classifier: Environment :: Web Environment
